{
  "classname": null,
  "name": null,
  "animation": {
    "classname": null,
    "name": "AnimationManager",
    "actionlist": []
  },
  "dataScale": 1,
  "designHeight": 960,
  "designWidth": 640,
  "textures": [],
  "version": "1.3.0.1",
  "widgetTree": {
    "classname": "Panel",
    "name": null,
    "children": [
      {
        "classname": "ImageView",
        "name": null,
        "children": [
          {
            "classname": "Button",
            "name": null,
            "children": [
              {
                "classname": "ImageView",
                "name": null,
                "children": [],
                "options": {
                  "__type": "ImageViewSurrogate:#EditorCommon.JsonModel.Component.GUI",
                  "classname": "ImageView",
                  "name": "ImageView_38",
                  "ZOrder": 0,
                  "actiontag": 38,
                  "anchorPointX": 0.5,
                  "anchorPointY": 0.5,
                  "classType": "ImageView",
                  "colorB": 255,
                  "colorG": 255,
                  "colorR": 255,
                  "customProperty": "",
                  "flipX": false,
                  "flipY": false,
                  "height": 31,
                  "ignoreSize": true,
                  "layoutParameter": null,
                  "opacity": 255,
                  "positionPercentX": 0,
                  "positionPercentY": 0,
                  "positionType": 0,
                  "rotation": 0,
                  "scaleX": 1,
                  "scaleY": 1,
                  "sizePercentX": 0.8357143,
                  "sizePercentY": 0.5344828,
                  "sizeType": 0,
                  "tag": 18,
                  "touchAble": false,
                  "useMergedTexture": false,
                  "visible": true,
                  "width": 117,
                  "x": 0,
                  "y": 0,
                  "capInsetsHeight": 1,
                  "capInsetsWidth": 1,
                  "capInsetsX": 0,
                  "capInsetsY": 0,
                  "fileName": null,
                  "fileNameData": {
                    "path": "text_yijianbuqi.png",
                    "plistFile": "",
                    "resourceType": 0
                  },
                  "scale9Enable": false,
                  "scale9Height": 31,
                  "scale9Width": 117
                }
              }
            ],
            "options": {
              "__type": "ButtonSurrogate:#EditorCommon.JsonModel.Component.GUI",
              "classname": "Button",
              "name": "Button_sure",
              "ZOrder": 0,
              "actiontag": 23,
              "anchorPointX": 0.5,
              "anchorPointY": 0.5,
              "classType": "Button",
              "colorB": 255,
              "colorG": 255,
              "colorR": 255,
              "customProperty": "",
              "flipX": false,
              "flipY": false,
              "height": 58,
              "ignoreSize": true,
              "layoutParameter": null,
              "opacity": 255,
              "positionPercentX": 0,
              "positionPercentY": -0.3908257,
              "positionType": 0,
              "rotation": 0,
              "scaleX": 1,
              "scaleY": 1,
              "sizePercentX": 0.246913582,
              "sizePercentY": 0.106422022,
              "sizeType": 0,
              "tag": 5,
              "touchAble": true,
              "useMergedTexture": false,
              "visible": true,
              "width": 140,
              "x": 0,
              "y": -213,
              "capInsetsHeight": 1,
              "capInsetsWidth": 1,
              "capInsetsX": 0,
              "capInsetsY": 0,
              "disabled": null,
              "disabledData": {
                "path": "public_newbuttom_4.png",
                "plistFile": "",
                "resourceType": 0
              },
              "fontName": "微软雅黑",
              "fontSize": 25,
              "fontType": 0,
              "normal": null,
              "normalData": {
                "path": "public_newbuttom_4.png",
                "plistFile": "",
                "resourceType": 0
              },
              "pressed": null,
              "pressedData": {
                "path": "public_newbuttom_4.png",
                "plistFile": "",
                "resourceType": 0
              },
              "scale9Enable": false,
              "scale9Height": 58,
              "scale9Width": 140,
              "text": "",
              "textColorB": 255,
              "textColorG": 255,
              "textColorR": 255
            }
          },
          {
            "classname": "Button",
            "name": null,
            "children": [],
            "options": {
              "__type": "ButtonSurrogate:#EditorCommon.JsonModel.Component.GUI",
              "classname": "Button",
              "name": "Button_cancle",
              "ZOrder": 4,
              "actiontag": 24,
              "anchorPointX": 0.5,
              "anchorPointY": 0.5,
              "classType": "Button",
              "colorB": 255,
              "colorG": 255,
              "colorR": 255,
              "customProperty": "",
              "flipX": false,
              "flipY": false,
              "height": 56,
              "ignoreSize": true,
              "layoutParameter": null,
              "opacity": 255,
              "positionPercentX": 0.449735463,
              "positionPercentY": 0.445871562,
              "positionType": 0,
              "rotation": 0,
              "scaleX": 1,
              "scaleY": 1,
              "sizePercentX": 0.09876543,
              "sizePercentY": 0.102752291,
              "sizeType": 0,
              "tag": 6,
              "touchAble": true,
              "useMergedTexture": false,
              "visible": true,
              "width": 56,
              "x": 255,
              "y": 243,
              "capInsetsHeight": 1,
              "capInsetsWidth": 1,
              "capInsetsX": 0,
              "capInsetsY": 0,
              "disabled": null,
              "disabledData": {
                "path": null,
                "plistFile": null,
                "resourceType": 0
              },
              "fontName": "微软雅黑",
              "fontSize": 25,
              "fontType": 0,
              "normal": null,
              "normalData": {
                "path": "public_gem_close.png",
                "plistFile": "",
                "resourceType": 0
              },
              "pressed": null,
              "pressedData": {
                "path": null,
                "plistFile": null,
                "resourceType": 0
              },
              "scale9Enable": false,
              "scale9Height": 56,
              "scale9Width": 56,
              "text": "",
              "textColorB": 255,
              "textColorG": 255,
              "textColorR": 255
            }
          },
          {
            "classname": "ImageView",
            "name": null,
            "children": [
              {
                "classname": "ImageView",
                "name": null,
                "children": [],
                "options": {
                  "__type": "ImageViewSurrogate:#EditorCommon.JsonModel.Component.GUI",
                  "classname": "ImageView",
                  "name": "ImageView_36",
                  "ZOrder": 0,
                  "actiontag": 36,
                  "anchorPointX": 0.5,
                  "anchorPointY": 0.5,
                  "classType": "ImageView",
                  "colorB": 255,
                  "colorG": 255,
                  "colorR": 255,
                  "customProperty": "",
                  "flipX": false,
                  "flipY": false,
                  "height": 53,
                  "ignoreSize": true,
                  "layoutParameter": null,
                  "opacity": 255,
                  "positionPercentX": 0,
                  "positionPercentY": 0.03076923,
                  "positionType": 0,
                  "rotation": 0,
                  "scaleX": 0.6999999,
                  "scaleY": 0.6999999,
                  "sizePercentX": 0.686131358,
                  "sizePercentY": 0.8153846,
                  "sizeType": 0,
                  "tag": 16,
                  "touchAble": false,
                  "useMergedTexture": false,
                  "visible": true,
                  "width": 188,
                  "x": 0,
                  "y": 2,
                  "capInsetsHeight": 1,
                  "capInsetsWidth": 1,
                  "capInsetsX": 0,
                  "capInsetsY": 0,
                  "fileName": null,
                  "fileNameData": {
                    "path": "text_suoxucailiao.png",
                    "plistFile": "",
                    "resourceType": 0
                  },
                  "scale9Enable": false,
                  "scale9Height": 53,
                  "scale9Width": 188
                }
              }
            ],
            "options": {
              "__type": "ImageViewSurrogate:#EditorCommon.JsonModel.Component.GUI",
              "classname": "ImageView",
              "name": "ImageView_35",
              "ZOrder": 4,
              "actiontag": 35,
              "anchorPointX": 0.5,
              "anchorPointY": 0.5,
              "classType": "ImageView",
              "colorB": 255,
              "colorG": 255,
              "colorR": 255,
              "customProperty": "",
              "flipX": false,
              "flipY": false,
              "height": 65,
              "ignoreSize": true,
              "layoutParameter": null,
              "opacity": 255,
              "positionPercentX": 0,
              "positionPercentY": 0.486238539,
              "positionType": 0,
              "rotation": 0,
              "scaleX": 1,
              "scaleY": 1,
              "sizePercentX": 0.483245164,
              "sizePercentY": 0.119266056,
              "sizeType": 0,
              "tag": 15,
              "touchAble": false,
              "useMergedTexture": false,
              "visible": true,
              "width": 274,
              "x": 0,
              "y": 265,
              "capInsetsHeight": 1,
              "capInsetsWidth": 1,
              "capInsetsX": 0,
              "capInsetsY": 0,
              "fileName": null,
              "fileNameData": {
                "path": "public_verb_1.png",
                "plistFile": "",
                "resourceType": 0
              },
              "scale9Enable": false,
              "scale9Height": 65,
              "scale9Width": 274
            }
          },
          {
            "classname": "ImageView",
            "name": null,
            "children": [
              {
                "classname": "ScrollView",
                "name": null,
                "children": [],
                "options": {
                  "__type": "ScrollViewSurrogate:#EditorCommon.JsonModel.Component.GUI",
                  "classname": "ScrollView",
                  "name": "ScrollView_list",
                  "ZOrder": 0,
                  "actiontag": 33,
                  "anchorPointX": 0,
                  "anchorPointY": 0,
                  "classType": "ScrollView",
                  "colorB": 255,
                  "colorG": 255,
                  "colorR": 255,
                  "customProperty": "",
                  "flipX": false,
                  "flipY": false,
                  "height": 340,
                  "ignoreSize": false,
                  "layoutParameter": null,
                  "opacity": 255,
                  "positionPercentX": -0.48879838,
                  "positionPercentY": -0.473239422,
                  "positionType": 0,
                  "rotation": 0,
                  "scaleX": 1,
                  "scaleY": 1,
                  "sizePercentX": 0.97759676,
                  "sizePercentY": 0.9577465,
                  "sizeType": 0,
                  "tag": 14,
                  "touchAble": true,
                  "useMergedTexture": false,
                  "visible": true,
                  "width": 480,
                  "x": -240,
                  "y": -168,
                  "backGroundImage": null,
                  "backGroundImageData": null,
                  "backGroundScale9Enable": false,
                  "bgColorB": 100,
                  "bgColorG": 150,
                  "bgColorOpacity": 100,
                  "bgColorR": 255,
                  "bgEndColorB": 100,
                  "bgEndColorG": 150,
                  "bgEndColorR": 255,
                  "bgStartColorB": 255,
                  "bgStartColorG": 255,
                  "bgStartColorR": 255,
                  "bounceEnable": false,
                  "capInsetsHeight": 1,
                  "capInsetsWidth": 1,
                  "capInsetsX": 0,
                  "capInsetsY": 0,
                  "clipAble": true,
                  "colorType": 0,
                  "direction": 1,
                  "innerHeight": 340,
                  "innerWidth": 480,
                  "layoutType": 0,
                  "vectorX": 0,
                  "vectorY": -0.5
                }
              }
            ],
            "options": {
              "__type": "ImageViewSurrogate:#EditorCommon.JsonModel.Component.GUI",
              "classname": "ImageView",
              "name": "ImageView_37",
              "ZOrder": 0,
              "actiontag": 37,
              "anchorPointX": 0.5,
              "anchorPointY": 0.5,
              "classType": "ImageView",
              "colorB": 255,
              "colorG": 255,
              "colorR": 255,
              "customProperty": "",
              "flipX": false,
              "flipY": false,
              "height": 355,
              "ignoreSize": false,
              "layoutParameter": null,
              "opacity": 255,
              "positionPercentX": 0,
              "positionPercentY": 0.110091746,
              "positionType": 0,
              "rotation": 0,
              "scaleX": 1,
              "scaleY": 1,
              "sizePercentX": 0.8659612,
              "sizePercentY": 0.6513761,
              "sizeType": 0,
              "tag": 17,
              "touchAble": false,
              "useMergedTexture": false,
              "visible": true,
              "width": 491,
              "x": 0,
              "y": 60,
              "capInsetsHeight": 1,
              "capInsetsWidth": 1,
              "capInsetsX": 20,
              "capInsetsY": 20,
              "fileName": null,
              "fileNameData": {
                "path": "public2_bg_19.png",
                "plistFile": "",
                "resourceType": 0
              },
              "scale9Enable": true,
              "scale9Height": 355,
              "scale9Width": 491
            }
          },
          {
            "classname": "ImageView",
            "name": null,
            "children": [
              {
                "classname": "ImageView",
                "name": null,
                "children": [],
                "options": {
                  "__type": "ImageViewSurrogate:#EditorCommon.JsonModel.Component.GUI",
                  "classname": "ImageView",
                  "name": "ImageView_40",
                  "ZOrder": 0,
                  "actiontag": 40,
                  "anchorPointX": 0.5,
                  "anchorPointY": 0.5,
                  "classType": "ImageView",
                  "colorB": 255,
                  "colorG": 255,
                  "colorR": 255,
                  "customProperty": "",
                  "flipX": false,
                  "flipY": false,
                  "height": 28,
                  "ignoreSize": true,
                  "layoutParameter": null,
                  "opacity": 255,
                  "positionPercentX": -0.285077959,
                  "positionPercentY": 0.04,
                  "positionType": 0,
                  "rotation": 0,
                  "scaleX": 1,
                  "scaleY": 1,
                  "sizePercentX": 0.365256131,
                  "sizePercentY": 0.56,
                  "sizeType": 0,
                  "tag": 20,
                  "touchAble": false,
                  "useMergedTexture": false,
                  "visible": true,
                  "width": 164,
                  "x": -128,
                  "y": 2,
                  "capInsetsHeight": 1,
                  "capInsetsWidth": 1,
                  "capInsetsX": 0,
                  "capInsetsY": 0,
                  "fileName": null,
                  "fileNameData": {
                    "path": "text_buqixiaohao.png",
                    "plistFile": "",
                    "resourceType": 0
                  },
                  "scale9Enable": false,
                  "scale9Height": 28,
                  "scale9Width": 164
                }
              },
              {
                "classname": "ImageView",
                "name": null,
                "children": [],
                "options": {
                  "__type": "ImageViewSurrogate:#EditorCommon.JsonModel.Component.GUI",
                  "classname": "ImageView",
                  "name": "ImageView_41",
                  "ZOrder": 0,
                  "actiontag": 41,
                  "anchorPointX": 0.5,
                  "anchorPointY": 0.5,
                  "classType": "ImageView",
                  "colorB": 255,
                  "colorG": 255,
                  "colorR": 255,
                  "customProperty": "",
                  "flipX": false,
                  "flipY": false,
                  "height": 36,
                  "ignoreSize": true,
                  "layoutParameter": null,
                  "opacity": 255,
                  "positionPercentX": 0,
                  "positionPercentY": 0.04,
                  "positionType": 0,
                  "rotation": 0,
                  "scaleX": 1,
                  "scaleY": 1,
                  "sizePercentX": 0.08017817,
                  "sizePercentY": 0.72,
                  "sizeType": 0,
                  "tag": 21,
                  "touchAble": false,
                  "useMergedTexture": false,
                  "visible": true,
                  "width": 36,
                  "x": 0,
                  "y": 2,
                  "capInsetsHeight": 1,
                  "capInsetsWidth": 1,
                  "capInsetsX": 0,
                  "capInsetsY": 0,
                  "fileName": null,
                  "fileNameData": {
                    "path": "rmbicon.png",
                    "plistFile": "",
                    "resourceType": 0
                  },
                  "scale9Enable": false,
                  "scale9Height": 36,
                  "scale9Width": 36
                }
              },
              {
                "classname": "Label",
                "name": null,
                "children": [],
                "options": {
                  "__type": "LabelSurrogate:#EditorCommon.JsonModel.Component.GUI",
                  "classname": "Label",
                  "name": "Label_allpay",
                  "ZOrder": 0,
                  "actiontag": 42,
                  "anchorPointX": 0,
                  "anchorPointY": 0.5,
                  "classType": "Label",
                  "colorB": 255,
                  "colorG": 255,
                  "colorR": 255,
                  "customProperty": "",
                  "flipX": false,
                  "flipY": false,
                  "height": 24,
                  "ignoreSize": true,
                  "layoutParameter": null,
                  "opacity": 255,
                  "positionPercentX": 0.113585748,
                  "positionPercentY": 0.04,
                  "positionType": 0,
                  "rotation": 0,
                  "scaleX": 1,
                  "scaleY": 1,
                  "sizePercentX": 0.106904231,
                  "sizePercentY": 0.48,
                  "sizeType": 0,
                  "tag": 22,
                  "touchAble": false,
                  "useMergedTexture": false,
                  "visible": true,
                  "width": 48,
                  "x": 51,
                  "y": 2,
                  "areaHeight": 0,
                  "areaWidth": 0,
                  "fontFile": null,
                  "fontName": "fzzdh.TTF",
                  "fontSize": 24,
                  "hAlignment": 0,
                  "text": "1000",
                  "touchScaleEnable": false,
                  "vAlignment": 0
                }
              }
            ],
            "options": {
              "__type": "ImageViewSurrogate:#EditorCommon.JsonModel.Component.GUI",
              "classname": "ImageView",
              "name": "ImageView_39",
              "ZOrder": 0,
              "actiontag": 39,
              "anchorPointX": 0.5,
              "anchorPointY": 0.5,
              "classType": "ImageView",
              "colorB": 255,
              "colorG": 255,
              "colorR": 255,
              "customProperty": "",
              "flipX": false,
              "flipY": false,
              "height": 50,
              "ignoreSize": false,
              "layoutParameter": null,
              "opacity": 255,
              "positionPercentX": 0,
              "positionPercentY": -0.278899074,
              "positionType": 0,
              "rotation": 0,
              "scaleX": 1,
              "scaleY": 1,
              "sizePercentX": 0.7918871,
              "sizePercentY": 0.09174312,
              "sizeType": 0,
              "tag": 19,
              "touchAble": false,
              "useMergedTexture": false,
              "visible": true,
              "width": 449,
              "x": 0,
              "y": -152,
              "capInsetsHeight": 1,
              "capInsetsWidth": 1,
              "capInsetsX": 20,
              "capInsetsY": 20,
              "fileName": null,
              "fileNameData": {
                "path": "public2_bg_19.png",
                "plistFile": "",
                "resourceType": 0
              },
              "scale9Enable": true,
              "scale9Height": 50,
              "scale9Width": 449
            }
          }
        ],
        "options": {
          "__type": "ImageViewSurrogate:#EditorCommon.JsonModel.Component.GUI",
          "classname": "ImageView",
          "name": "background",
          "ZOrder": 0,
          "actiontag": 25,
          "anchorPointX": 0.5,
          "anchorPointY": 0.5,
          "classType": "ImageView",
          "colorB": 255,
          "colorG": 255,
          "colorR": 255,
          "customProperty": "",
          "flipX": false,
          "flipY": false,
          "height": 545,
          "ignoreSize": false,
          "layoutParameter": null,
          "opacity": 255,
          "positionPercentX": 0.5,
          "positionPercentY": 0.5,
          "positionType": 0,
          "rotation": 0,
          "scaleX": 1,
          "scaleY": 1,
          "sizePercentX": 0.8859375,
          "sizePercentY": 0.5677083,
          "sizeType": 0,
          "tag": 7,
          "touchAble": false,
          "useMergedTexture": false,
          "visible": true,
          "width": 567,
          "x": 320,
          "y": 480,
          "capInsetsHeight": 1,
          "capInsetsWidth": 1,
          "capInsetsX": 90,
          "capInsetsY": 90,
          "fileName": null,
          "fileNameData": {
            "path": "public2_bg_04.png",
            "plistFile": "",
            "resourceType": 0
          },
          "scale9Enable": true,
          "scale9Height": 545,
          "scale9Width": 567
        }
      }
    ],
    "options": {
      "__type": "PanelSurrogate:#EditorCommon.JsonModel.Component.GUI",
      "classname": "Panel",
      "name": "Panel_20",
      "ZOrder": 0,
      "actiontag": -1,
      "anchorPointX": 0,
      "anchorPointY": 0,
      "classType": "Panel",
      "colorB": 255,
      "colorG": 255,
      "colorR": 255,
      "customProperty": "",
      "flipX": false,
      "flipY": false,
      "height": 960,
      "ignoreSize": false,
      "layoutParameter": null,
      "opacity": 255,
      "positionPercentX": 0,
      "positionPercentY": 0,
      "positionType": 0,
      "rotation": 0,
      "scaleX": 1,
      "scaleY": 1,
      "sizePercentX": 0,
      "sizePercentY": 0,
      "sizeType": 0,
      "tag": 3,
      "touchAble": true,
      "useMergedTexture": false,
      "visible": true,
      "width": 640,
      "x": 0,
      "y": 0,
      "adaptScreen": false,
      "backGroundImage": null,
      "backGroundImageData": null,
      "backGroundScale9Enable": false,
      "bgColorB": 0,
      "bgColorG": 0,
      "bgColorOpacity": 128,
      "bgColorR": 0,
      "bgEndColorB": 255,
      "bgEndColorG": 200,
      "bgEndColorR": 150,
      "bgStartColorB": 255,
      "bgStartColorG": 255,
      "bgStartColorR": 255,
      "capInsetsHeight": 1,
      "capInsetsWidth": 1,
      "capInsetsX": 0,
      "capInsetsY": 0,
      "clipAble": false,
      "colorType": 1,
      "layoutType": 0,
      "vectorX": 0,
      "vectorY": -0.5
    }
  }
}